getpartofimg/README.MD
getpartofimg/__init__.py
getpartofimg/requirements.txt
getpartofimg/thirdparty.json
getpartofimg-0.10.dist-info/LICENSE.rst
getpartofimg-0.10.dist-info/METADATA
getpartofimg-0.10.dist-info/WHEEL
getpartofimg-0.10.dist-info/top_level.txt
getpartofimg-0.10.dist-info/RECORD
